django_tweets/__init__.py
django_tweets/admin.py
django_tweets/apps.py
django_tweets/clients.py
django_tweets/decorators.py
django_tweets/exceptions.py
django_tweets/models.py
django_tweets/migrations/0001_initial.py
django_tweets/migrations/0002_remove_mediafile_upload.py
django_tweets/migrations/0003_mediafileupload.py
django_tweets/migrations/0004_rename_mediafile_tweetfile_and_more.py
django_tweets/migrations/0005_alter_tweet_edit_history_tweet_ids_and_more.py
django_tweets/migrations/0006_tweetfile_delete_after_upload.py
django_tweets/migrations/__init__.py
django_tweets-0.0.9.dist-info/LICENSE
django_tweets-0.0.9.dist-info/METADATA
django_tweets-0.0.9.dist-info/WHEEL
django_tweets-0.0.9.dist-info/top_level.txt
django_tweets-0.0.9.dist-info/RECORD
