Metadata-Version: 2.1
Name: django-tweets
Version: 0.0.9
Summary: An app to manage tweets in a Django project
Author-email: Rami <ramiboutas@protonmail.com>
Project-URL: Homepage, https://github.com/ramiboutas/django-tweets
Project-URL: Bug Tracker, https://github.com/ramiboutas/django-tweets/issues
Classifier: Programming Language :: Python :: 3
Classifier: License :: OSI Approved :: MIT License
Classifier: Operating System :: OS Independent
Classifier: Framework :: Django
Classifier: Framework :: Django :: 4
Requires-Python: >=3.7
License-File: LICENSE
Requires-Dist: tweepy
Requires-Dist: django
